CHANGES.txt
LICENSE.txt
MANIFEST.in
README.txt
setup.cfg
setup.py
frapwings/__init__.py
frapwings.skels.egg-info/PKG-INFO
frapwings.skels.egg-info/SOURCES.txt
frapwings.skels.egg-info/dependency_links.txt
frapwings.skels.egg-info/entry_points.txt
frapwings.skels.egg-info/namespace_packages.txt
frapwings.skels.egg-info/not-zip-safe
frapwings.skels.egg-info/requires.txt
frapwings.skels.egg-info/top_level.txt
frapwings/skels/__init__.py
frapwings/skels/package.py
frapwings/skels/tests/__init__.py
frapwings/skels/tests/test_package.py
frapwings/skels/tmpl/package/.gitignore_tmpl
frapwings/skels/tmpl/package/CHANGES.txt_tmpl
frapwings/skels/tmpl/package/LICENSE.txt_tmpl
frapwings/skels/tmpl/package/MANIFEST.in_tmpl
frapwings/skels/tmpl/package/README.txt_tmpl
frapwings/skels/tmpl/package/setup.py_tmpl
frapwings/skels/tmpl/package/+namespace_package+/__init__.py_tmpl
frapwings/skels/tmpl/package/+namespace_package+/+package+/__init__.py_tmpl