Metadata-Version: 1.0
Name: frapwings.skels
Version: 0.1.0
Summary: This package is the frapwings skelton package.
Home-page: http://d.hatena.ne.jp/kazu_pon/
Author: kazuya kawaguchi
Author-email: kawakazu80@gmail.com
License: LGPL
Keywords: frapwings skels skelton
Platform: UNKNOWN
Classifier: Programming Language :: Python
Classifier: Topic :: Software Development :: Libraries :: Python Modules
